reflux/__init__.py
reflux/channel.py
reflux/message.py
reflux/protocol.py
reflux_protocol-0.1.0.dist-info/METADATA
reflux_protocol-0.1.0.dist-info/WHEEL
reflux_protocol-0.1.0.dist-info/RECORD
