Metadata-Version: 2.4
Name: reflux-protocol
Version: 0.1.0
Summary: REsilient Low-frequency Universal eXchange - Out-of-band AI communication over radio, satellite, and phone lines
Project-URL: Homepage, https://humotica.com
Project-URL: Repository, https://github.com/jaspertvdm/reflux
Project-URL: Documentation, https://humotica.com/docs/reflux
Author-email: Jasper van de Meent <info@humotica.com>, Root AI <root_ai@humotica.nl>
License: MIT
Keywords: agentic-ai,ai,communication,disaster-recovery,ham-radio,humotica,out-of-band,radio,resilience,satellite,sstv
Classifier: Development Status :: 3 - Alpha
Classifier: Intended Audience :: Developers
Classifier: Intended Audience :: Science/Research
Classifier: Intended Audience :: Telecommunications Industry
Classifier: License :: OSI Approved :: MIT License
Classifier: Operating System :: OS Independent
Classifier: Programming Language :: Python :: 3
Classifier: Programming Language :: Python :: 3.10
Classifier: Programming Language :: Python :: 3.11
Classifier: Programming Language :: Python :: 3.12
Classifier: Programming Language :: Python :: 3.13
Classifier: Topic :: Communications :: Ham Radio
Classifier: Topic :: Scientific/Engineering :: Artificial Intelligence
Classifier: Topic :: System :: Recovery Tools
Requires-Python: >=3.10
Requires-Dist: pysstv>=0.5
Provides-Extra: full
Requires-Dist: pillow>=10.0; extra == 'full'
Requires-Dist: pyzbar>=0.1; extra == 'full'
Requires-Dist: qrcode>=7.0; extra == 'full'
Requires-Dist: sensory>=0.1.0; extra == 'full'
